{"cameraMode":{"drawMode":0,"name":"Shaded","section":"Shading Mode"},"sceneLighting":true,"audioPlay":false,"sceneViewState":{"m_AlwaysRefresh":false,"showFog":true,"showSkybox":true,"showFlares":true,"showImageEffects":true,"showParticleSystems":true,"showVisualEffectGraphs":true,"m_FxEnabled":true},"in2DMode":false,"pivot":{"x":4.617957592010498,"y":2.287292957305908,"z":18.918943405151368},"rotation":{"x":0.0017888201400637627,"y":-0.14913585782051087,"z":0.0002795169421005994,"w":0.9888285994529724},"size":26.997140884399415,"orthographic":false}